{"1": "modular_analog_io_1_pin_1", "2": "modular_analog_io_1_pin_2", "3": "modular_analog_io_1_pin_3", "4": "modular_analog_io_1_pin_4", "5": "modular_analog_io_1_pin_5", "6": "modular_analog_io_1_pin_6", "7": "modular_analog_io_1_pin_7", "8": "modular_analog_io_1_pin_8", "9": "modular_analog_io_2_pin_1", "10": "modular_analog_io_2_pin_2", "11": "modular_analog_io_2_pin_3", "12": "modular_analog_io_2_pin_4", "13": "modular_analog_io_2_pin_5", "14": "modular_analog_io_2_pin_6", "15": "modular_analog_io_2_pin_7", "16": "modular_analog_io_2_pin_8", "17": "modular_drycontact_1_pin_1", "18": "modular_drycontact_1_pin_2", "19": "modular_drycontact_1_pin_3", "20": "modular_drycontact_1_pin_4", "21": "modular_drycontact_1_pin_5", "22": "modular_drycontact_1_pin_6", "23": "modular_drycontact_1_pin_7", "24": "modular_drycontact_1_pin_8", "25": "modular_drycontact_2_pin_1", "26": "modular_drycontact_2_pin_2", "27": "modular_drycontact_2_pin_3", "28": "modular_drycontact_2_pin_4", "29": "modular_drycontact_2_pin_5", "30": "modular_drycontact_2_pin_6", "31": "modular_drycontact_2_pin_7", "32": "modular_drycontact_2_pin_8", "33": "modular_drycontact_3_pin_1", "34": "modular_drycontact_3_pin_2", "35": "modular_drycontact_3_pin_3", "36": "modular_drycontact_3_pin_4", "37": "modular_drycontact_3_pin_5", "38": "modular_drycontact_3_pin_6", "39": "modular_drycontact_3_pin_7", "40": "modular_drycontact_3_pin_8", "41": "modular_drycontact_4_pin_1", "42": "modular_drycontact_4_pin_2", "43": "modular_drycontact_4_pin_3", "44": "modular_drycontact_4_pin_4", "45": "modular_drycontact_4_pin_5", "46": "modular_drycontact_4_pin_6", "47": "modular_drycontact_4_pin_7", "48": "modular_drycontact_4_pin_8", "49": "modular_drycontact_5_pin_1", "50": "modular_drycontact_5_pin_2", "51": "modular_drycontact_5_pin_3", "52": "modular_drycontact_5_pin_4", "53": "modular_drycontact_5_pin_5", "54": "modular_drycontact_5_pin_6", "55": "modular_drycontact_5_pin_7", "56": "modular_drycontact_5_pin_8", "57": "modular_drycontact_6_pin_1", "58": "modular_drycontact_6_pin_2", "59": "modular_drycontact_6_pin_3", "60": "modular_drycontact_6_pin_4", "61": "modular_drycontact_6_pin_5", "62": "modular_drycontact_6_pin_6", "63": "modular_drycontact_6_pin_7", "64": "modular_drycontact_6_pin_8", "65": "modular_drycontact_7_pin_1", "66": "modular_drycontact_7_pin_2", "67": "modular_drycontact_7_pin_3", "68": "modular_drycontact_7_pin_4", "69": "modular_drycontact_7_pin_5", "70": "modular_drycontact_7_pin_6", "71": "modular_drycontact_7_pin_7", "72": "modular_drycontact_7_pin_8", "73": "modular_drycontact_8_pin_1", "74": "modular_drycontact_8_pin_2", "75": "modular_drycontact_8_pin_3", "76": "modular_drycontact_8_pin_4", "77": "modular_drycontact_8_pin_5", "78": "modular_drycontact_8_pin_6", "79": "modular_drycontact_8_pin_7", "80": "modular_drycontact_8_pin_8", "81": "modular_gpio_1_pin_1", "82": "modular_gpio_1_pin_2", "83": "modular_gpio_1_pin_3", "84": "modular_gpio_1_pin_4", "85": "modular_gpio_1_pin_5", "86": "modular_gpio_1_pin_6", "87": "modular_gpio_1_pin_7", "88": "modular_gpio_1_pin_8", "89": "modular_gpio_2_pin_1", "90": "modular_gpio_2_pin_2", "91": "modular_gpio_2_pin_3", "92": "modular_gpio_2_pin_4", "93": "modular_gpio_2_pin_5", "94": "modular_gpio_2_pin_6", "95": "modular_gpio_2_pin_7", "96": "modular_gpio_2_pin_8", "97": "modular_gpio_3_pin_1", "98": "modular_gpio_3_pin_2", "99": "modular_gpio_3_pin_3", "100": "modular_gpio_3_pin_4", "101": "modular_gpio_3_pin_5", "102": "modular_gpio_3_pin_6", "103": "modular_gpio_3_pin_7", "104": "modular_gpio_3_pin_8", "105": "modular_gpio_4_pin_1", "106": "modular_gpio_4_pin_2", "107": "modular_gpio_4_pin_3", "108": "modular_gpio_4_pin_4", "109": "modular_gpio_4_pin_5", "110": "modular_gpio_4_pin_6", "111": "modular_gpio_4_pin_7", "112": "modular_gpio_4_pin_8", "113": "modular_gpio_5_pin_1", "114": "modular_gpio_5_pin_2", "115": "modular_gpio_5_pin_3", "116": "modular_gpio_5_pin_4", "117": "modular_gpio_5_pin_5", "118": "modular_gpio_5_pin_6", "119": "modular_gpio_5_pin_7", "120": "modular_gpio_5_pin_8", "121": "modular_gpio_6_pin_1", "122": "modular_gpio_6_pin_2", "123": "modular_gpio_6_pin_3", "124": "modular_gpio_6_pin_4", "125": "modular_gpio_6_pin_5", "126": "modular_gpio_6_pin_6", "127": "modular_gpio_6_pin_7", "128": "modular_gpio_6_pin_8", "129": "modular_gpio_7_pin_1", "130": "modular_gpio_7_pin_2", "131": "modular_gpio_7_pin_3", "132": "modular_gpio_7_pin_4", "133": "modular_gpio_7_pin_5", "134": "modular_gpio_7_pin_6", "135": "modular_gpio_7_pin_7", "136": "modular_gpio_7_pin_8", "137": "modular_gpio_8_pin_1", "138": "modular_gpio_8_pin_2", "139": "modular_gpio_8_pin_3", "140": "modular_gpio_8_pin_4", "141": "modular_gpio_8_pin_5", "142": "modular_gpio_8_pin_6", "143": "modular_gpio_8_pin_7", "144": "modular_gpio_8_pin_8", "145": "modular_optocoupler_1_pin_1", "146": "modular_optocoupler_1_pin_2", "147": "modular_optocoupler_1_pin_3", "148": "modular_optocoupler_1_pin_4", "149": "modular_optocoupler_1_pin_5", "150": "modular_optocoupler_1_pin_6", "151": "modular_optocoupler_1_pin_7", "152": "modular_optocoupler_1_pin_8", "153": "modular_optocoupler_2_pin_1", "154": "modular_optocoupler_2_pin_2", "155": "modular_optocoupler_2_pin_3", "156": "modular_optocoupler_2_pin_4", "157": "modular_optocoupler_2_pin_5", "158": "modular_optocoupler_2_pin_6", "159": "modular_optocoupler_2_pin_7", "160": "modular_optocoupler_2_pin_8", "161": "modular_optocoupler_3_pin_1", "162": "modular_optocoupler_3_pin_2", "163": "modular_optocoupler_3_pin_3", "164": "modular_optocoupler_3_pin_4", "165": "modular_optocoupler_3_pin_5", "166": "modular_optocoupler_3_pin_6", "167": "modular_optocoupler_3_pin_7", "168": "modular_optocoupler_3_pin_8", "169": "modular_optocoupler_4_pin_1", "170": "modular_optocoupler_4_pin_2", "171": "modular_optocoupler_4_pin_3", "172": "modular_optocoupler_4_pin_4", "173": "modular_optocoupler_4_pin_5", "174": "modular_optocoupler_4_pin_6", "175": "modular_optocoupler_4_pin_7", "176": "modular_optocoupler_4_pin_8", "177": "modular_optocoupler_5_pin_1", "178": "modular_optocoupler_5_pin_2", "179": "modular_optocoupler_5_pin_3", "180": "modular_optocoupler_5_pin_4", "181": "modular_optocoupler_5_pin_5", "182": "modular_optocoupler_5_pin_6", "183": "modular_optocoupler_5_pin_7", "184": "modular_optocoupler_5_pin_8", "185": "modular_optocoupler_6_pin_1", "186": "modular_optocoupler_6_pin_2", "187": "modular_optocoupler_6_pin_3", "188": "modular_optocoupler_6_pin_4", "189": "modular_optocoupler_6_pin_5", "190": "modular_optocoupler_6_pin_6", "191": "modular_optocoupler_6_pin_7", "192": "modular_optocoupler_6_pin_8", "193": "modular_optocoupler_7_pin_1", "194": "modular_optocoupler_7_pin_2", "195": "modular_optocoupler_7_pin_3", "196": "modular_optocoupler_7_pin_4", "197": "modular_optocoupler_7_pin_5", "198": "modular_optocoupler_7_pin_6", "199": "modular_optocoupler_7_pin_7", "200": "modular_optocoupler_7_pin_8", "201": "modular_optocoupler_8_pin_1", "202": "modular_optocoupler_8_pin_2", "203": "modular_optocoupler_8_pin_3", "204": "modular_optocoupler_8_pin_4", "205": "modular_optocoupler_8_pin_5", "206": "modular_optocoupler_8_pin_6", "207": "modular_optocoupler_8_pin_7", "208": "modular_optocoupler_8_pin_8", "209": "modular_relay_1_pin_1", "210": "modular_relay_1_pin_2", "211": "modular_relay_1_pin_3", "212": "modular_relay_1_pin_4", "213": "modular_relay_1_pin_5", "214": "modular_relay_1_pin_6", "215": "modular_relay_1_pin_7", "216": "modular_relay_1_pin_8", "217": "modular_relay_2_pin_1", "218": "modular_relay_2_pin_2", "219": "modular_relay_2_pin_3", "220": "modular_relay_2_pin_4", "221": "modular_relay_2_pin_5", "222": "modular_relay_2_pin_6", "223": "modular_relay_2_pin_7", "224": "modular_relay_2_pin_8", "225": "modular_relay_3_pin_1", "226": "modular_relay_3_pin_2", "227": "modular_relay_3_pin_3", "228": "modular_relay_3_pin_4", "229": "modular_relay_3_pin_5", "230": "modular_relay_3_pin_6", "231": "modular_relay_3_pin_7", "232": "modular_relay_3_pin_8", "233": "modular_relay_4_pin_1", "234": "modular_relay_4_pin_2", "235": "modular_relay_4_pin_3", "236": "modular_relay_4_pin_4", "237": "modular_relay_4_pin_5", "238": "modular_relay_4_pin_6", "239": "modular_relay_4_pin_7", "240": "modular_relay_4_pin_8", "241": "modular_relay_5_pin_1", "242": "modular_relay_5_pin_2", "243": "modular_relay_5_pin_3", "244": "modular_relay_5_pin_4", "245": "modular_relay_5_pin_5", "246": "modular_relay_5_pin_6", "247": "modular_relay_5_pin_7", "248": "modular_relay_5_pin_8", "249": "modular_relay_6_pin_1", "250": "modular_relay_6_pin_2", "251": "modular_relay_6_pin_3", "252": "modular_relay_6_pin_4", "253": "modular_relay_6_pin_5", "254": "modular_relay_6_pin_6", "255": "modular_relay_6_pin_7", "256": "modular_relay_6_pin_8", "257": "modular_relay_7_pin_1", "258": "modular_relay_7_pin_2", "259": "modular_relay_7_pin_3", "260": "modular_relay_7_pin_4", "261": "modular_relay_7_pin_5", "262": "modular_relay_7_pin_6", "263": "modular_relay_7_pin_7", "264": "modular_relay_7_pin_8", "265": "modular_relay_8_pin_1", "266": "modular_relay_8_pin_2", "267": "modular_relay_8_pin_3", "268": "modular_relay_8_pin_4", "269": "modular_relay_8_pin_5", "270": "modular_relay_8_pin_6", "271": "modular_relay_8_pin_7", "272": "modular_relay_8_pin_8", "273": "modular_relay_mini_1_pin_1", "274": "modular_relay_mini_1_pin_2", "275": "modular_relay_mini_1_pin_3", "276": "modular_relay_mini_1_pin_4", "277": "modular_relay_mini_1_pin_5", "278": "modular_relay_mini_1_pin_6", "279": "modular_relay_mini_2_pin_1", "280": "modular_relay_mini_2_pin_2", "281": "modular_relay_mini_2_pin_3", "282": "modular_relay_mini_2_pin_4", "283": "modular_relay_mini_2_pin_5", "284": "modular_relay_mini_2_pin_6", "285": "modular_relay_mini_3_pin_1", "286": "modular_relay_mini_3_pin_2", "287": "modular_relay_mini_3_pin_3", "288": "modular_relay_mini_3_pin_4", "289": "modular_relay_mini_3_pin_5", "290": "modular_relay_mini_3_pin_6", "291": "modular_relay_mini_4_pin_1", "292": "modular_relay_mini_4_pin_2", "293": "modular_relay_mini_4_pin_3", "294": "modular_relay_mini_4_pin_4", "295": "modular_relay_mini_4_pin_5", "296": "modular_relay_mini_4_pin_6", "297": "modular_relay_mini_5_pin_1", "298": "modular_relay_mini_5_pin_2", "299": "modular_relay_mini_5_pin_3", "300": "modular_relay_mini_5_pin_4", "301": "modular_relay_mini_5_pin_5", "302": "modular_relay_mini_5_pin_6", "303": "modular_relay_mini_6_pin_1", "304": "modular_relay_mini_6_pin_2", "305": "modular_relay_mini_6_pin_3", "306": "modular_relay_mini_6_pin_4", "307": "modular_relay_mini_6_pin_5", "308": "modular_relay_mini_6_pin_6", "309": "modular_relay_mini_7_pin_1", "310": "modular_relay_mini_7_pin_2", "311": "modular_relay_mini_7_pin_3", "312": "modular_relay_mini_7_pin_4", "313": "modular_relay_mini_7_pin_5", "314": "modular_relay_mini_7_pin_6", "315": "modular_relay_mini_8_pin_1", "316": "modular_relay_mini_8_pin_2", "317": "modular_relay_mini_8_pin_3", "318": "modular_relay_mini_8_pin_4", "319": "modular_relay_mini_8_pin_5", "320": "modular_relay_mini_8_pin_6", "1001": "detect_motion-Motion_Sensor_1"}